pyqt5span/__init__.py
pyqt5span/qspanheadermodel.py
pyqt5span/qspanheaderview.py
pyqt5span/qspantableview.py
pyqt5span-0.1.2.dist-info/LICENSE
pyqt5span-0.1.2.dist-info/METADATA
pyqt5span-0.1.2.dist-info/WHEEL
pyqt5span-0.1.2.dist-info/top_level.txt
pyqt5span-0.1.2.dist-info/RECORD
