Metadata-Version: 2.1
Name: pyqt5span
Version: 0.1.2
Summary: Span header for PyQt5
Home-page: https://github.com/glourencoffee/pyqt5span
Author: Edwin Yllanes, Giovanni Lourenço
Author-email: gvnl.developer@outlook.com
License: MIT
Keywords: pyqt5,spanning
Requires-Python: >=3.7
License-File: LICENSE
Requires-Dist: PyQt5
